README
setup.py
dispatching_dns/__init__.py
dispatching_dns/_core.py
dispatching_dns/server.py
dispatching_dns.egg-info/PKG-INFO
dispatching_dns.egg-info/SOURCES.txt
dispatching_dns.egg-info/dependency_links.txt
dispatching_dns.egg-info/entry_points.txt
dispatching_dns.egg-info/requires.txt
dispatching_dns.egg-info/top_level.txt