Metadata-Version: 1.0
Name: dispatching-dns
Version: 0.0.20
Summary: A simple suboptimal dns server which forward requests to multiple servers according to domains
Home-page: https://github.com/sherwoodwang/dispatching-dns
Author: Sherwood Wang
Author-email: sherwood@wang.onl
License: 2-clause BSD
Platform: UNKNOWN
